ofxstatement_jl_partnership-1.0.0-nspkg.pth
ofxstatement/plugins/jlpartnership.py
ofxstatement_jl_partnership-1.0.0.dist-info/LICENSE.txt
ofxstatement_jl_partnership-1.0.0.dist-info/METADATA
ofxstatement_jl_partnership-1.0.0.dist-info/WHEEL
ofxstatement_jl_partnership-1.0.0.dist-info/entry_points.txt
ofxstatement_jl_partnership-1.0.0.dist-info/namespace_packages.txt
ofxstatement_jl_partnership-1.0.0.dist-info/top_level.txt
ofxstatement_jl_partnership-1.0.0.dist-info/zip-safe
ofxstatement_jl_partnership-1.0.0.dist-info/RECORD
