Metadata-Version: 2.1
Name: ofxstatement-jl-partnership
Version: 1.0.0
Summary: OFXStatement plugin for John Lewis Partnership card (UK)
Home-page: https://github.com/daniel-beet/ofxstatement-jl-partnership
Author: Daniel Beet
Author-email: dan@ionicblue.com
License: MIT
Keywords: ofx,banking,statement,john lewis,partnership
Platform: UNKNOWN
Classifier: Development Status :: 5 - Production/Stable
Classifier: Programming Language :: Python :: 3
Classifier: Natural Language :: English
Classifier: Topic :: Office/Business :: Financial :: Accounting
Classifier: Topic :: Utilities
Classifier: Environment :: Console
Classifier: Operating System :: OS Independent
Classifier: License :: OSI Approved :: MIT License
Requires-Dist: ofxstatement
